song/__init__.py
song/duplex_song.py
song/duplex_umap_song.py
song/song.py
song/umap_song.py
song/util.py
song_vis-1.4.0.0.dist-info/LICENSE.txt
song_vis-1.4.0.0.dist-info/METADATA
song_vis-1.4.0.0.dist-info/WHEEL
song_vis-1.4.0.0.dist-info/top_level.txt
song_vis-1.4.0.0.dist-info/RECORD
