Metadata-Version: 2.1
Name: song-vis
Version: 1.4.0.0
Summary: A dimensionality reduction method that retains a parametric model
Download-URL: https://github.com/damithsenanayake/SONG/archive/v1.1.1.tar.gz
Author: Damith Senanayake
Author-email: dracusds123@gmail.com
License-File: LICENSE.txt
